embykeeper/__init__.py
embykeeper/__main__.py
embykeeper/apprise.py
embykeeper/cache.py
embykeeper/clean.py
embykeeper/cli.py
embykeeper/cloudflare.py
embykeeper/config.py
embykeeper/data.py
embykeeper/log.py
embykeeper/notify.py
embykeeper/ocr.py
embykeeper/public.py
embykeeper/runinfo.py
embykeeper/schedule.py
embykeeper/schema.py
embykeeper/topper.py
embykeeper/utils.py
embykeeper/var.py
embykeeper/windows.py
embykeeper/wssocks.py
embykeeper/emby/__init__.py
embykeeper/emby/api.py
embykeeper/emby/main.py
embykeeper/subsonic/__init__.py
embykeeper/subsonic/api.py
embykeeper/subsonic/main.py
embykeeper/subsonic/player.py
embykeeper/telegram/__init__.py
embykeeper/telegram/checkin_main.py
embykeeper/telegram/debug.py
embykeeper/telegram/dynamic.py
embykeeper/telegram/embyboss.py
embykeeper/telegram/link.py
embykeeper/telegram/lock.py
embykeeper/telegram/log.py
embykeeper/telegram/message_main.py
embykeeper/telegram/monitor_main.py
embykeeper/telegram/pyrogram.py
embykeeper/telegram/registrar_main.py
embykeeper/telegram/session.py
embykeeper/telegram/telethon.py
embykeeper/telegram/checkiner/__init__.py
embykeeper/telegram/checkiner/_base.py
embykeeper/telegram/checkiner/_templ_a.py
embykeeper/telegram/checkiner/_templ_b.py
embykeeper/telegram/checkiner/_templ_c.py
embykeeper/telegram/checkiner/agentsgk.py
embykeeper/telegram/checkiner/aisgk.py
embykeeper/telegram/checkiner/aivbi.py
embykeeper/telegram/checkiner/akile.py
embykeeper/telegram/checkiner/akile_group.py
embykeeper/telegram/checkiner/akuai.py
embykeeper/telegram/checkiner/alpha.py
embykeeper/telegram/checkiner/apop.py
embykeeper/telegram/checkiner/apoppro.py
embykeeper/telegram/checkiner/ask.py
embykeeper/telegram/checkiner/aurora.py
embykeeper/telegram/checkiner/awamusic.py
embykeeper/telegram/checkiner/awatv.py
embykeeper/telegram/checkiner/baidusgk.py
embykeeper/telegram/checkiner/bearsgk.py
embykeeper/telegram/checkiner/bibi.py
embykeeper/telegram/checkiner/bingdaosgk.py
embykeeper-7.5.2.dist-info/licenses/LICENSE
embykeeper-7.5.2.dist-info/METADATA
embykeeper-7.5.2.dist-info/WHEEL
embykeeper-7.5.2.dist-info/entry_points.txt
embykeeper-7.5.2.dist-info/top_level.txt
embykeeper-7.5.2.dist-info/RECORD
