Metadata-Version: 2.4
Name: embykeeper
Version: 7.5.2
Summary: Daily checkin automator for emby bots in telegram.
Author-email: jackzzs <jackzzs@outlook.com>
Project-URL: Homepage, https://github.com/emby-keeper/emby-keeper
Keywords: emby,telegram,checkin,automator,bot,telegram bot,keep active
Classifier: Development Status :: 5 - Production/Stable
Classifier: Environment :: Console
Classifier: Environment :: Web Environment
Classifier: Intended Audience :: End Users/Desktop
Classifier: Natural Language :: Chinese (Simplified)
Classifier: License :: OSI Approved :: GNU General Public License v3 (GPLv3)
Classifier: Programming Language :: Python :: 3
Classifier: Programming Language :: Python :: 3.8
Classifier: Programming Language :: Python :: 3.9
Classifier: Programming Language :: Python :: 3.10
Classifier: Programming Language :: Python :: 3.11
Classifier: Programming Language :: Python :: 3.12
Classifier: Programming Language :: Python :: 3.13
Requires-Python: >=3.8
License-File: LICENSE
Requires-Dist: pyyaml
Requires-Dist: tomli
Requires-Dist: tomlkit
Requires-Dist: rich
Requires-Dist: typer
Requires-Dist: appdirs
Requires-Dist: loguru
Requires-Dist: faker
Requires-Dist: aiofiles
Requires-Dist: python-dateutil
Requires-Dist: ddddocrfix>=1.5.5
Requires-Dist: embygram==2025.09.20
Requires-Dist: tgcrypto
Requires-Dist: pillow>10.0.0
Requires-Dist: thefuzz[speedup]
Requires-Dist: aiocache
Requires-Dist: flask==3.0.3
Requires-Dist: flask-socketio==5.3.6
Requires-Dist: flask-login==0.6.3
Requires-Dist: simple-websocket
Requires-Dist: eventlet
Requires-Dist: cryptography
Requires-Dist: werkzeug==3.0.3
Requires-Dist: cachetools
Requires-Dist: emoji
Requires-Dist: numpy<2.0.0
Requires-Dist: httpx[http2]
Requires-Dist: socksio
Requires-Dist: telethon
Requires-Dist: psutil
Requires-Dist: xpinyin
Requires-Dist: curl_cffi
Requires-Dist: pymongo
Requires-Dist: pydantic
Requires-Dist: watchfiles
Requires-Dist: python-socks[asyncio]
Requires-Dist: apprise
Requires-Dist: fastapi
Requires-Dist: uvicorn[standard]
Dynamic: license-file
